README.md
setup.cfg
setup.py
yahtzee_api/__init__.py
yahtzee_api/constants.py
yahtzee_api/game.py
yahtzee_api/player.py
yahtzee_api/test.py
yahtzee_api.egg-info/PKG-INFO
yahtzee_api.egg-info/SOURCES.txt
yahtzee_api.egg-info/dependency_links.txt
yahtzee_api.egg-info/top_level.txt