Metadata-Version: 1.1
Name: yahtzee-api
Version: 1.1.1
Summary: A general purpose API to play an n-player game of Yahtzee
Home-page: https://github.com/tomarbeiter/yahtzee_api
Author: Tom Arbeiter
Author-email: UNKNOWN
License: Apache 2.0
Platform: UNKNOWN
Classifier: Programming Language :: Python :: 3
Classifier: License :: OSI Approved :: Apache Software License
Classifier: Intended Audience :: Developers
